AUTHORS.rst
LICENSE
MANIFEST.in
README.md
requirements.txt
setup.cfg
setup.py
pythoncheck321/__init__.py
pythoncheck321/common.py
pythoncheck321/pythoncheck321.py
pythoncheck321.egg-info/PKG-INFO
pythoncheck321.egg-info/SOURCES.txt
pythoncheck321.egg-info/dependency_links.txt
pythoncheck321.egg-info/not-zip-safe
pythoncheck321.egg-info/top_level.txt
tests/test_pythoncheck321.py