Metadata-Version: 2.1
Name: pythoncheck321
Version: 0.0.1
Summary: Python Boilerplate contains all the boilerplate you need to create a Python package.
Home-page: https://github.com/knop-k/pythoncheck321
Author: Krzysiek Knop
Author-email: admin@example.com
License: MIT license
Keywords: pythoncheck321
Classifier: Intended Audience :: Developers
Classifier: License :: OSI Approved :: MIT License
Classifier: Natural Language :: English
Classifier: Programming Language :: Python :: 3
Classifier: Programming Language :: Python :: 3.8
Classifier: Programming Language :: Python :: 3.9
Classifier: Programming Language :: Python :: 3.10
Classifier: Programming Language :: Python :: 3.11
Requires-Python: >=3.8
License-File: LICENSE
License-File: AUTHORS.rst
